{
  "station": {
    "id": "noaa/8571201",
    "name": "Long Point, Big Annemessex River",
    "sourceName": "US National Oceanic and Atmospheric Administration",
    "sourceId": "8571201",
    "sourceUrl": "https://tidesandcurrents.noaa.gov/stationhome.html?id=8571201",
    "license": "public domain",
    "licenseUrl": "https://tidesandcurrents.noaa.gov/disclaimers.html",
    "commercialUse": true,
    "stationType": "subordinate",
    "referenceStationId": "noaa/8638863",
    "country": "United States",
    "region": "MD",
    "continent": "Americas",
    "timezone": "America/New_York",
    "latitude": 38.0567,
    "longitude": -75.8033,
    "chartDatum": "MLLW",
    "datumsSource": null,
    "qualityAccepted": true,
    "quality": "No obvious issues"
  },
  "generatedAt": "2026-07-13T05:48:25.667Z",
  "validFrom": "2026-07-13T00:00:00.000Z",
  "validTo": "2026-08-27T00:00:00.000Z",
  "days": 45,
  "units": {
    "height": "m above chart datum",
    "time": "UTC"
  },
  "disclaimer": "Tide predictions are informational and not for navigation.",
  "attribution": "Tide harmonic constituents and subordinate station offsets from the Neaps tide database (https://github.com/openwatersio/tide-database).",
  "events": [
    {
      "time": "2026-07-13T11:38:05.859Z",
      "type": "low",
      "heightM": -0.022
    },
    {
      "time": "2026-07-13T17:07:06.165Z",
      "type": "high",
      "heightM": 0.617
    },
    {
      "time": "2026-07-13T23:31:00.290Z",
      "type": "low",
      "heightM": -0.049
    },
    {
      "time": "2026-07-14T05:39:17.205Z",
      "type": "high",
      "heightM": 0.854
    },
    {
      "time": "2026-07-14T12:32:22.753Z",
      "type": "low",
      "heightM": -0.045
    },
    {
      "time": "2026-07-14T18:05:06.848Z",
      "type": "high",
      "heightM": 0.652
    },
    {
      "time": "2026-07-15T00:29:54.873Z",
      "type": "low",
      "heightM": -0.065
    },
    {
      "time": "2026-07-15T06:34:08.896Z",
      "type": "high",
      "heightM": 0.854
    },
    {
      "time": "2026-07-15T13:22:08.780Z",
      "type": "low",
      "heightM": -0.057
    },
    {
      "time": "2026-07-15T18:59:09.414Z",
      "type": "high",
      "heightM": 0.684
    },
    {
      "time": "2026-07-16T01:25:19.313Z",
      "type": "low",
      "heightM": -0.065
    },
    {
      "time": "2026-07-16T07:25:35.218Z",
      "type": "high",
      "heightM": 0.834
    },
    {
      "time": "2026-07-16T14:09:26.069Z",
      "type": "low",
      "heightM": -0.056
    },
    {
      "time": "2026-07-16T19:51:05.757Z",
      "type": "high",
      "heightM": 0.706
    },
    {
      "time": "2026-07-17T02:19:29.384Z",
      "type": "low",
      "heightM": -0.045
    },
    {
      "time": "2026-07-17T08:15:11.011Z",
      "type": "high",
      "heightM": 0.795
    },
    {
      "time": "2026-07-17T14:56:16.749Z",
      "type": "low",
      "heightM": -0.041
    },
    {
      "time": "2026-07-17T20:42:42.314Z",
      "type": "high",
      "heightM": 0.717
    },
    {
      "time": "2026-07-18T03:15:31.350Z",
      "type": "low",
      "heightM": -0.009
    },
    {
      "time": "2026-07-18T09:03:50.174Z",
      "type": "high",
      "heightM": 0.742
    },
    {
      "time": "2026-07-18T15:43:40.179Z",
      "type": "low",
      "heightM": -0.017
    },
    {
      "time": "2026-07-18T21:33:55.674Z",
      "type": "high",
      "heightM": 0.72
    },
    {
      "time": "2026-07-19T04:14:32.074Z",
      "type": "low",
      "heightM": 0.035
    },
    {
      "time": "2026-07-19T09:51:14.286Z",
      "type": "high",
      "heightM": 0.682
    },
    {
      "time": "2026-07-19T16:31:02.244Z",
      "type": "low",
      "heightM": 0.011
    },
    {
      "time": "2026-07-19T22:23:43.748Z",
      "type": "high",
      "heightM": 0.713
    },
    {
      "time": "2026-07-20T05:14:19.875Z",
      "type": "low",
      "heightM": 0.077
    },
    {
      "time": "2026-07-20T10:37:15.159Z",
      "type": "high",
      "heightM": 0.621
    },
    {
      "time": "2026-07-20T17:17:26.997Z",
      "type": "low",
      "heightM": 0.042
    },
    {
      "time": "2026-07-20T23:12:33.145Z",
      "type": "high",
      "heightM": 0.7
    },
    {
      "time": "2026-07-21T06:13:47.208Z",
      "type": "low",
      "heightM": 0.115
    },
    {
      "time": "2026-07-21T11:23:35.819Z",
      "type": "high",
      "heightM": 0.565
    },
    {
      "time": "2026-07-21T18:03:31.282Z",
      "type": "low",
      "heightM": 0.073
    },
    {
      "time": "2026-07-22T00:03:21.942Z",
      "type": "high",
      "heightM": 0.683
    },
    {
      "time": "2026-07-22T07:14:19.358Z",
      "type": "low",
      "heightM": 0.142
    },
    {
      "time": "2026-07-22T12:14:31.439Z",
      "type": "high",
      "heightM": 0.519
    },
    {
      "time": "2026-07-22T18:51:24.050Z",
      "type": "low",
      "heightM": 0.101
    },
    {
      "time": "2026-07-23T01:00:13.032Z",
      "type": "high",
      "heightM": 0.67
    },
    {
      "time": "2026-07-23T08:14:32.404Z",
      "type": "low",
      "heightM": 0.156
    },
    {
      "time": "2026-07-23T13:15:34.974Z",
      "type": "high",
      "heightM": 0.49
    },
    {
      "time": "2026-07-23T19:42:40.138Z",
      "type": "low",
      "heightM": 0.121
    },
    {
      "time": "2026-07-24T02:01:00.875Z",
      "type": "high",
      "heightM": 0.664
    },
    {
      "time": "2026-07-24T09:10:08.443Z",
      "type": "low",
      "heightM": 0.159
    },
    {
      "time": "2026-07-24T14:21:12.105Z",
      "type": "high",
      "heightM": 0.484
    },
    {
      "time": "2026-07-24T20:35:31.064Z",
      "type": "low",
      "heightM": 0.13
    },
    {
      "time": "2026-07-25T02:56:19.174Z",
      "type": "high",
      "heightM": 0.668
    },
    {
      "time": "2026-07-25T10:00:41.548Z",
      "type": "low",
      "heightM": 0.153
    },
    {
      "time": "2026-07-25T15:17:57.737Z",
      "type": "high",
      "heightM": 0.495
    },
    {
      "time": "2026-07-25T21:27:04.210Z",
      "type": "low",
      "heightM": 0.129
    },
    {
      "time": "2026-07-26T03:45:18.806Z",
      "type": "high",
      "heightM": 0.678
    },
    {
      "time": "2026-07-26T10:47:38.368Z",
      "type": "low",
      "heightM": 0.14
    },
    {
      "time": "2026-07-26T16:07:36.259Z",
      "type": "high",
      "heightM": 0.517
    },
    {
      "time": "2026-07-26T22:17:05.247Z",
      "type": "low",
      "heightM": 0.12
    },
    {
      "time": "2026-07-27T04:30:54.435Z",
      "type": "high",
      "heightM": 0.69
    },
    {
      "time": "2026-07-27T11:30:47.306Z",
      "type": "low",
      "heightM": 0.124
    },
    {
      "time": "2026-07-27T16:53:32.356Z",
      "type": "high",
      "heightM": 0.546
    },
    {
      "time": "2026-07-27T23:05:42.363Z",
      "type": "low",
      "heightM": 0.104
    },
    {
      "time": "2026-07-28T05:13:49.727Z",
      "type": "high",
      "heightM": 0.703
    },
    {
      "time": "2026-07-28T12:09:10.367Z",
      "type": "low",
      "heightM": 0.105
    },
    {
      "time": "2026-07-28T17:36:18.778Z",
      "type": "high",
      "heightM": 0.577
    },
    {
      "time": "2026-07-28T23:51:28.909Z",
      "type": "low",
      "heightM": 0.088
    },
    {
      "time": "2026-07-29T05:53:42.167Z",
      "type": "high",
      "heightM": 0.713
    },
    {
      "time": "2026-07-29T12:43:16.206Z",
      "type": "low",
      "heightM": 0.086
    },
    {
      "time": "2026-07-29T18:16:07.807Z",
      "type": "high",
      "heightM": 0.608
    },
    {
      "time": "2026-07-30T00:33:28.254Z",
      "type": "low",
      "heightM": 0.075
    },
    {
      "time": "2026-07-30T06:30:54.270Z",
      "type": "high",
      "heightM": 0.717
    },
    {
      "time": "2026-07-30T13:14:47.850Z",
      "type": "low",
      "heightM": 0.07
    },
    {
      "time": "2026-07-30T18:54:02.212Z",
      "type": "high",
      "heightM": 0.635
    },
    {
      "time": "2026-07-31T01:12:49.308Z",
      "type": "low",
      "heightM": 0.068
    },
    {
      "time": "2026-07-31T07:06:43.817Z",
      "type": "high",
      "heightM": 0.715
    },
    {
      "time": "2026-07-31T13:45:50.155Z",
      "type": "low",
      "heightM": 0.057
    },
    {
      "time": "2026-07-31T19:31:30.007Z",
      "type": "high",
      "heightM": 0.658
    },
    {
      "time": "2026-08-01T01:51:45.801Z",
      "type": "low",
      "heightM": 0.069
    },
    {
      "time": "2026-08-01T07:42:42.233Z",
      "type": "high",
      "heightM": 0.705
    },
    {
      "time": "2026-08-01T14:18:19.110Z",
      "type": "low",
      "heightM": 0.05
    },
    {
      "time": "2026-08-01T20:09:56.479Z",
      "type": "high",
      "heightM": 0.68
    },
    {
      "time": "2026-08-02T02:32:45.787Z",
      "type": "low",
      "heightM": 0.076
    },
    {
      "time": "2026-08-02T08:20:16.852Z",
      "type": "high",
      "heightM": 0.688
    },
    {
      "time": "2026-08-02T14:53:49.553Z",
      "type": "low",
      "heightM": 0.047
    },
    {
      "time": "2026-08-02T20:50:27.127Z",
      "type": "high",
      "heightM": 0.699
    },
    {
      "time": "2026-08-03T03:18:07.088Z",
      "type": "low",
      "heightM": 0.089
    },
    {
      "time": "2026-08-03T09:00:34.536Z",
      "type": "high",
      "heightM": 0.666
    },
    {
      "time": "2026-08-03T15:33:36.535Z",
      "type": "low",
      "heightM": 0.05
    },
    {
      "time": "2026-08-03T21:33:34.018Z",
      "type": "high",
      "heightM": 0.717
    },
    {
      "time": "2026-08-04T04:09:07.484Z",
      "type": "low",
      "heightM": 0.102
    },
    {
      "time": "2026-08-04T09:44:08.036Z",
      "type": "high",
      "heightM": 0.64
    },
    {
      "time": "2026-08-04T16:18:16.216Z",
      "type": "low",
      "heightM": 0.056
    },
    {
      "time": "2026-08-04T22:19:37.621Z",
      "type": "high",
      "heightM": 0.733
    },
    {
      "time": "2026-08-05T05:05:07.403Z",
      "type": "low",
      "heightM": 0.114
    },
    {
      "time": "2026-08-05T10:31:19.867Z",
      "type": "high",
      "heightM": 0.611
    },
    {
      "time": "2026-08-05T17:07:43.822Z",
      "type": "low",
      "heightM": 0.063
    },
    {
      "time": "2026-08-05T23:09:46.845Z",
      "type": "high",
      "heightM": 0.745
    },
    {
      "time": "2026-08-06T06:05:35.459Z",
      "type": "low",
      "heightM": 0.122
    },
    {
      "time": "2026-08-06T11:23:43.502Z",
      "type": "high",
      "heightM": 0.583
    },
    {
      "time": "2026-08-06T18:02:27.325Z",
      "type": "low",
      "heightM": 0.071
    },
    {
      "time": "2026-08-07T00:07:01.815Z",
      "type": "high",
      "heightM": 0.753
    },
    {
      "time": "2026-08-07T07:11:42.610Z",
      "type": "low",
      "heightM": 0.124
    },
    {
      "time": "2026-08-07T12:25:21.151Z",
      "type": "high",
      "heightM": 0.562
    },
    {
      "time": "2026-08-07T19:03:57.469Z",
      "type": "low",
      "heightM": 0.074
    },
    {
      "time": "2026-08-08T01:14:11.737Z",
      "type": "high",
      "heightM": 0.764
    },
    {
      "time": "2026-08-08T08:20:40.333Z",
      "type": "low",
      "heightM": 0.112
    },
    {
      "time": "2026-08-08T13:38:15.626Z",
      "type": "high",
      "heightM": 0.56
    },
    {
      "time": "2026-08-08T20:10:56.474Z",
      "type": "low",
      "heightM": 0.066
    },
    {
      "time": "2026-08-09T02:25:17.046Z",
      "type": "high",
      "heightM": 0.786
    },
    {
      "time": "2026-08-09T09:25:40.620Z",
      "type": "low",
      "heightM": 0.089
    },
    {
      "time": "2026-08-09T14:51:09.419Z",
      "type": "high",
      "heightM": 0.584
    },
    {
      "time": "2026-08-09T21:17:32.281Z",
      "type": "low",
      "heightM": 0.046
    },
    {
      "time": "2026-08-10T03:30:57.589Z",
      "type": "high",
      "heightM": 0.815
    },
    {
      "time": "2026-08-10T10:25:52.984Z",
      "type": "low",
      "heightM": 0.059
    },
    {
      "time": "2026-08-10T15:56:26.081Z",
      "type": "high",
      "heightM": 0.625
    },
    {
      "time": "2026-08-10T22:21:31.845Z",
      "type": "low",
      "heightM": 0.019
    },
    {
      "time": "2026-08-11T04:31:21.551Z",
      "type": "high",
      "heightM": 0.839
    },
    {
      "time": "2026-08-11T11:22:03.819Z",
      "type": "low",
      "heightM": 0.027
    },
    {
      "time": "2026-08-11T16:56:26.164Z",
      "type": "high",
      "heightM": 0.673
    },
    {
      "time": "2026-08-11T23:23:08.812Z",
      "type": "low",
      "heightM": -0.006
    },
    {
      "time": "2026-08-12T05:27:16.012Z",
      "type": "high",
      "heightM": 0.852
    },
    {
      "time": "2026-08-12T12:13:12.403Z",
      "type": "low",
      "heightM": -0.001
    },
    {
      "time": "2026-08-12T17:51:28.770Z",
      "type": "high",
      "heightM": 0.722
    },
    {
      "time": "2026-08-13T00:20:33.334Z",
      "type": "low",
      "heightM": -0.022
    },
    {
      "time": "2026-08-13T06:18:08.220Z",
      "type": "high",
      "heightM": 0.849
    },
    {
      "time": "2026-08-13T12:59:17.370Z",
      "type": "low",
      "heightM": -0.018
    },
    {
      "time": "2026-08-13T18:41:44.136Z",
      "type": "high",
      "heightM": 0.76
    },
    {
      "time": "2026-08-14T01:13:07.885Z",
      "type": "low",
      "heightM": -0.021
    },
    {
      "time": "2026-08-14T07:04:45.937Z",
      "type": "high",
      "heightM": 0.827
    },
    {
      "time": "2026-08-14T13:41:52.193Z",
      "type": "low",
      "heightM": -0.02
    },
    {
      "time": "2026-08-14T19:28:52.555Z",
      "type": "high",
      "heightM": 0.785
    },
    {
      "time": "2026-08-15T02:02:57.324Z",
      "type": "low",
      "heightM": 0
    },
    {
      "time": "2026-08-15T07:48:53.551Z",
      "type": "high",
      "heightM": 0.788
    },
    {
      "time": "2026-08-15T14:22:49.450Z",
      "type": "low",
      "heightM": -0.006
    },
    {
      "time": "2026-08-15T20:14:43.194Z",
      "type": "high",
      "heightM": 0.792
    },
    {
      "time": "2026-08-16T02:52:52.903Z",
      "type": "low",
      "heightM": 0.038
    },
    {
      "time": "2026-08-16T08:32:04.536Z",
      "type": "high",
      "heightM": 0.737
    },
    {
      "time": "2026-08-16T15:03:42.613Z",
      "type": "low",
      "heightM": 0.022
    },
    {
      "time": "2026-08-16T21:00:12.000Z",
      "type": "high",
      "heightM": 0.786
    },
    {
      "time": "2026-08-17T03:45:07.668Z",
      "type": "low",
      "heightM": 0.085
    },
    {
      "time": "2026-08-17T09:15:08.015Z",
      "type": "high",
      "heightM": 0.681
    },
    {
      "time": "2026-08-17T15:45:37.864Z",
      "type": "low",
      "heightM": 0.059
    },
    {
      "time": "2026-08-17T21:45:15.561Z",
      "type": "high",
      "heightM": 0.768
    },
    {
      "time": "2026-08-18T04:39:47.077Z",
      "type": "low",
      "heightM": 0.133
    },
    {
      "time": "2026-08-18T09:58:21.046Z",
      "type": "high",
      "heightM": 0.627
    },
    {
      "time": "2026-08-18T16:29:06.588Z",
      "type": "low",
      "heightM": 0.1
    },
    {
      "time": "2026-08-18T22:29:57.290Z",
      "type": "high",
      "heightM": 0.742
    },
    {
      "time": "2026-08-19T05:35:35.397Z",
      "type": "low",
      "heightM": 0.173
    },
    {
      "time": "2026-08-19T10:42:24.567Z",
      "type": "high",
      "heightM": 0.58
    },
    {
      "time": "2026-08-19T17:14:33.348Z",
      "type": "low",
      "heightM": 0.139
    },
    {
      "time": "2026-08-19T23:16:02.939Z",
      "type": "high",
      "heightM": 0.714
    },
    {
      "time": "2026-08-20T06:33:26.528Z",
      "type": "low",
      "heightM": 0.205
    },
    {
      "time": "2026-08-20T11:29:54.819Z",
      "type": "high",
      "heightM": 0.541
    },
    {
      "time": "2026-08-20T18:03:29.568Z",
      "type": "low",
      "heightM": 0.171
    },
    {
      "time": "2026-08-21T00:07:49.048Z",
      "type": "high",
      "heightM": 0.689
    },
    {
      "time": "2026-08-21T07:34:39.615Z",
      "type": "low",
      "heightM": 0.224
    },
    {
      "time": "2026-08-21T12:26:40.451Z",
      "type": "high",
      "heightM": 0.517
    },
    {
      "time": "2026-08-21T18:58:43.773Z",
      "type": "low",
      "heightM": 0.193
    },
    {
      "time": "2026-08-22T01:10:58.806Z",
      "type": "high",
      "heightM": 0.673
    },
    {
      "time": "2026-08-22T08:34:00.125Z",
      "type": "low",
      "heightM": 0.227
    },
    {
      "time": "2026-08-22T13:37:46.443Z",
      "type": "high",
      "heightM": 0.515
    },
    {
      "time": "2026-08-22T19:59:35.027Z",
      "type": "low",
      "heightM": 0.199
    },
    {
      "time": "2026-08-23T02:18:28.513Z",
      "type": "high",
      "heightM": 0.675
    },
    {
      "time": "2026-08-23T09:26:06.020Z",
      "type": "low",
      "heightM": 0.218
    },
    {
      "time": "2026-08-23T14:44:35.214Z",
      "type": "high",
      "heightM": 0.535
    },
    {
      "time": "2026-08-23T20:58:22.106Z",
      "type": "low",
      "heightM": 0.19
    },
    {
      "time": "2026-08-24T03:14:33.890Z",
      "type": "high",
      "heightM": 0.69
    },
    {
      "time": "2026-08-24T10:11:58.024Z",
      "type": "low",
      "heightM": 0.2
    },
    {
      "time": "2026-08-24T15:37:09.083Z",
      "type": "high",
      "heightM": 0.571
    },
    {
      "time": "2026-08-24T21:51:40.323Z",
      "type": "low",
      "heightM": 0.17
    },
    {
      "time": "2026-08-25T04:01:45.721Z",
      "type": "high",
      "heightM": 0.709
    },
    {
      "time": "2026-08-25T10:53:25.301Z",
      "type": "low",
      "heightM": 0.175
    },
    {
      "time": "2026-08-25T16:22:54.263Z",
      "type": "high",
      "heightM": 0.612
    },
    {
      "time": "2026-08-25T22:41:07.246Z",
      "type": "low",
      "heightM": 0.145
    },
    {
      "time": "2026-08-26T04:44:19.180Z",
      "type": "high",
      "heightM": 0.729
    },
    {
      "time": "2026-08-26T11:31:09.472Z",
      "type": "low",
      "heightM": 0.146
    },
    {
      "time": "2026-08-26T17:05:22.946Z",
      "type": "high",
      "heightM": 0.656
    },
    {
      "time": "2026-08-26T23:27:29.270Z",
      "type": "low",
      "heightM": 0.12
    }
  ]
}
